pygamelive/__init__.py
pygamelive/debugger.py
pygamelive-1.0.0.dist-info/LICENSE
pygamelive-1.0.0.dist-info/METADATA
pygamelive-1.0.0.dist-info/WHEEL
pygamelive-1.0.0.dist-info/top_level.txt
pygamelive-1.0.0.dist-info/RECORD
