Metadata-Version: 2.1
Name: pygamelive
Version: 1.0.0
Summary: Live coding in your pygame projects!
Author-email: ElsevarAsadov <elseverclash57@gmail.com>
License: BSD Zero Clause License
Project-URL: Homepage, https://github.com/ElsevarAsadov/PygameLive
Keywords: python,pygame,livecoding
Classifier: License :: OSI Approved :: MIT License
Classifier: Programming Language :: Python
Classifier: Programming Language :: Python :: 3
Requires-Python: >=3.2
License-File: LICENSE
